<?xml version="1.0" encoding="utf-8" standalone="yes"?>
<Gesture Name = "1">
	<Stroke>
		<Point X = "653" Y = "-485" T = "0" Pressure = "0" />
		<Point X = "653" Y = "-485" T = "0" Pressure = "0" />
		<Point X = "653" Y = "-485" T = "0" Pressure = "0" />
		<Point X = "653" Y = "-485" T = "0" Pressure = "0" />
		<Point X = "655" Y = "-484" T = "0" Pressure = "0" />
		<Point X = "655" Y = "-484" T = "0" Pressure = "0" />
		<Point X = "659" Y = "-486" T = "0" Pressure = "0" />
		<Point X = "664" Y = "-488" T = "0" Pressure = "0" />
		<Point X = "669" Y = "-492" T = "0" Pressure = "0" />
		<Point X = "682" Y = "-499" T = "0" Pressure = "0" />
		<Point X = "682" Y = "-499" T = "0" Pressure = "0" />
		<Point X = "695" Y = "-507" T = "0" Pressure = "0" />
		<Point X = "751" Y = "-545" T = "0" Pressure = "0" />
		<Point X = "771" Y = "-559" T = "0" Pressure = "0" />
		<Point X = "788" Y = "-574" T = "0" Pressure = "0" />
		<Point X = "829" Y = "-616" T = "0" Pressure = "0" />
		<Point X = "829" Y = "-616" T = "0" Pressure = "0" />
		<Point X = "859" Y = "-668" T = "0" Pressure = "0" />
		<Point X = "864" Y = "-681" T = "0" Pressure = "0" />
		<Point X = "864" Y = "-681" T = "0" Pressure = "0" />
		<Point X = "868" Y = "-692" T = "0" Pressure = "0" />
		<Point X = "874" Y = "-707" T = "0" Pressure = "0" />
		<Point X = "874" Y = "-709" T = "0" Pressure = "0" />
		<Point X = "875" Y = "-711" T = "0" Pressure = "0" />
		<Point X = "875" Y = "-711" T = "0" Pressure = "0" />
		<Point X = "875" Y = "-711" T = "0" Pressure = "0" />
		<Point X = "875" Y = "-711" T = "0" Pressure = "0" />
		<Point X = "875" Y = "-711" T = "0" Pressure = "0" />
		<Point X = "875" Y = "-711" T = "0" Pressure = "0" />
		<Point X = "875" Y = "-711" T = "0" Pressure = "0" />
		<Point X = "875" Y = "-711" T = "0" Pressure = "0" />
		<Point X = "875" Y = "-711" T = "0" Pressure = "0" />
		<Point X = "875" Y = "-711" T = "0" Pressure = "0" />
		<Point X = "875" Y = "-711" T = "0" Pressure = "0" />
		<Point X = "875" Y = "-711" T = "0" Pressure = "0" />
		<Point X = "875" Y = "-711" T = "0" Pressure = "0" />
		<Point X = "875" Y = "-711" T = "0" Pressure = "0" />
		<Point X = "875" Y = "-711" T = "0" Pressure = "0" />
		<Point X = "875" Y = "-711" T = "0" Pressure = "0" />
		<Point X = "875" Y = "-711" T = "0" Pressure = "0" />
		<Point X = "875" Y = "-711" T = "0" Pressure = "0" />
		<Point X = "875" Y = "-697" T = "0" Pressure = "0" />
		<Point X = "875" Y = "-688" T = "0" Pressure = "0" />
		<Point X = "875" Y = "-677" T = "0" Pressure = "0" />
		<Point X = "875" Y = "-666" T = "0" Pressure = "0" />
		<Point X = "875" Y = "-666" T = "0" Pressure = "0" />
		<Point X = "875" Y = "-636" T = "0" Pressure = "0" />
		<Point X = "875" Y = "-619" T = "0" Pressure = "0" />
		<Point X = "875" Y = "-602" T = "0" Pressure = "0" />
		<Point X = "875" Y = "-602" T = "0" Pressure = "0" />
		<Point X = "875" Y = "-602" T = "0" Pressure = "0" />
		<Point X = "876" Y = "-521" T = "0" Pressure = "0" />
		<Point X = "876" Y = "-521" T = "0" Pressure = "0" />
		<Point X = "876" Y = "-501" T = "0" Pressure = "0" />
		<Point X = "876" Y = "-482" T = "0" Pressure = "0" />
		<Point X = "876" Y = "-463" T = "0" Pressure = "0" />
		<Point X = "876" Y = "-443" T = "0" Pressure = "0" />
		<Point X = "876" Y = "-443" T = "0" Pressure = "0" />
		<Point X = "876" Y = "-428" T = "0" Pressure = "0" />
		<Point X = "876" Y = "-418" T = "0" Pressure = "0" />
		<Point X = "876" Y = "-405" T = "0" Pressure = "0" />
		<Point X = "876" Y = "-396" T = "0" Pressure = "0" />
		<Point X = "876" Y = "-396" T = "0" Pressure = "0" />
		<Point X = "876" Y = "-387" T = "0" Pressure = "0" />
		<Point X = "876" Y = "-381" T = "0" Pressure = "0" />
		<Point X = "876" Y = "-376" T = "0" Pressure = "0" />
		<Point X = "876" Y = "-376" T = "0" Pressure = "0" />
		<Point X = "876" Y = "-374" T = "0" Pressure = "0" />
		<Point X = "876" Y = "-372" T = "0" Pressure = "0" />
		<Point X = "876" Y = "-372" T = "0" Pressure = "0" />
		<Point X = "876" Y = "-372" T = "0" Pressure = "0" />
		<Point X = "876" Y = "-372" T = "0" Pressure = "0" />
		<Point X = "876" Y = "-372" T = "0" Pressure = "0" />
		<Point X = "876" Y = "-372" T = "0" Pressure = "0" />
		<Point X = "876" Y = "-372" T = "0" Pressure = "0" />
		<Point X = "876" Y = "-372" T = "0" Pressure = "0" />
		<Point X = "876" Y = "-372" T = "0" Pressure = "0" />
		<Point X = "876" Y = "-372" T = "0" Pressure = "0" />
		<Point X = "876" Y = "-372" T = "0" Pressure = "0" />
		<Point X = "876" Y = "-372" T = "0" Pressure = "0" />
		<Point X = "876" Y = "-372" T = "0" Pressure = "0" />
		<Point X = "876" Y = "-372" T = "0" Pressure = "0" />
		<Point X = "876" Y = "-372" T = "0" Pressure = "0" />
		<Point X = "876" Y = "-372" T = "0" Pressure = "0" />
		<Point X = "876" Y = "-372" T = "0" Pressure = "0" />
		<Point X = "877" Y = "-372" T = "0" Pressure = "0" />
		<Point X = "877" Y = "-372" T = "0" Pressure = "0" />
		<Point X = "877" Y = "-372" T = "0" Pressure = "0" />
		<Point X = "877" Y = "-372" T = "0" Pressure = "0" />
		<Point X = "877" Y = "-372" T = "0" Pressure = "0" />
		<Point X = "878" Y = "-372" T = "0" Pressure = "0" />
		<Point X = "878" Y = "-372" T = "0" Pressure = "0" />
	</Stroke>
</Gesture>
