<?xml version="1.0" encoding="utf-8" standalone="yes"?>
<Gesture Name = "v">
	<Stroke>
		<Point X = "671" Y = "-617" T = "0" Pressure = "0" />
		<Point X = "671" Y = "-617" T = "0" Pressure = "0" />
		<Point X = "670" Y = "-616" T = "0" Pressure = "0" />
		<Point X = "670" Y = "-616" T = "0" Pressure = "0" />
		<Point X = "670" Y = "-608" T = "0" Pressure = "0" />
		<Point X = "670" Y = "-608" T = "0" Pressure = "0" />
		<Point X = "670" Y = "-603" T = "0" Pressure = "0" />
		<Point X = "670" Y = "-595" T = "0" Pressure = "0" />
		<Point X = "674" Y = "-574" T = "0" Pressure = "0" />
		<Point X = "678" Y = "-560" T = "0" Pressure = "0" />
		<Point X = "684" Y = "-545" T = "0" Pressure = "0" />
		<Point X = "687" Y = "-527" T = "0" Pressure = "0" />
		<Point X = "692" Y = "-510" T = "0" Pressure = "0" />
		<Point X = "698" Y = "-490" T = "0" Pressure = "0" />
		<Point X = "709" Y = "-452" T = "0" Pressure = "0" />
		<Point X = "716" Y = "-429" T = "0" Pressure = "0" />
		<Point X = "716" Y = "-429" T = "0" Pressure = "0" />
		<Point X = "722" Y = "-410" T = "0" Pressure = "0" />
		<Point X = "725" Y = "-393" T = "0" Pressure = "0" />
		<Point X = "731" Y = "-377" T = "0" Pressure = "0" />
		<Point X = "735" Y = "-363" T = "0" Pressure = "0" />
		<Point X = "742" Y = "-338" T = "0" Pressure = "0" />
		<Point X = "743" Y = "-333" T = "0" Pressure = "0" />
		<Point X = "745" Y = "-325" T = "0" Pressure = "0" />
		<Point X = "745" Y = "-325" T = "0" Pressure = "0" />
		<Point X = "745" Y = "-324" T = "0" Pressure = "0" />
		<Point X = "745" Y = "-324" T = "0" Pressure = "0" />
		<Point X = "745" Y = "-324" T = "0" Pressure = "0" />
		<Point X = "745" Y = "-324" T = "0" Pressure = "0" />
		<Point X = "745" Y = "-324" T = "0" Pressure = "0" />
		<Point X = "745" Y = "-324" T = "0" Pressure = "0" />
		<Point X = "745" Y = "-324" T = "0" Pressure = "0" />
		<Point X = "745" Y = "-324" T = "0" Pressure = "0" />
		<Point X = "745" Y = "-324" T = "0" Pressure = "0" />
		<Point X = "745" Y = "-324" T = "0" Pressure = "0" />
		<Point X = "745" Y = "-324" T = "0" Pressure = "0" />
		<Point X = "745" Y = "-324" T = "0" Pressure = "0" />
		<Point X = "745" Y = "-324" T = "0" Pressure = "0" />
		<Point X = "745" Y = "-324" T = "0" Pressure = "0" />
		<Point X = "745" Y = "-324" T = "0" Pressure = "0" />
		<Point X = "745" Y = "-324" T = "0" Pressure = "0" />
		<Point X = "745" Y = "-324" T = "0" Pressure = "0" />
		<Point X = "745" Y = "-324" T = "0" Pressure = "0" />
		<Point X = "745" Y = "-324" T = "0" Pressure = "0" />
		<Point X = "745" Y = "-324" T = "0" Pressure = "0" />
		<Point X = "745" Y = "-324" T = "0" Pressure = "0" />
		<Point X = "745" Y = "-324" T = "0" Pressure = "0" />
		<Point X = "745" Y = "-324" T = "0" Pressure = "0" />
		<Point X = "745" Y = "-324" T = "0" Pressure = "0" />
		<Point X = "745" Y = "-324" T = "0" Pressure = "0" />
		<Point X = "745" Y = "-324" T = "0" Pressure = "0" />
		<Point X = "745" Y = "-324" T = "0" Pressure = "0" />
		<Point X = "745" Y = "-324" T = "0" Pressure = "0" />
		<Point X = "745" Y = "-324" T = "0" Pressure = "0" />
		<Point X = "748" Y = "-333" T = "0" Pressure = "0" />
		<Point X = "749" Y = "-345" T = "0" Pressure = "0" />
		<Point X = "755" Y = "-363" T = "0" Pressure = "0" />
		<Point X = "762" Y = "-381" T = "0" Pressure = "0" />
		<Point X = "771" Y = "-400" T = "0" Pressure = "0" />
		<Point X = "780" Y = "-419" T = "0" Pressure = "0" />
		<Point X = "788" Y = "-440" T = "0" Pressure = "0" />
		<Point X = "797" Y = "-462" T = "0" Pressure = "0" />
		<Point X = "807" Y = "-483" T = "0" Pressure = "0" />
		<Point X = "815" Y = "-502" T = "0" Pressure = "0" />
		<Point X = "831" Y = "-539" T = "0" Pressure = "0" />
		<Point X = "837" Y = "-553" T = "0" Pressure = "0" />
		<Point X = "844" Y = "-567" T = "0" Pressure = "0" />
		<Point X = "844" Y = "-567" T = "0" Pressure = "0" />
		<Point X = "851" Y = "-582" T = "0" Pressure = "0" />
		<Point X = "860" Y = "-596" T = "0" Pressure = "0" />
		<Point X = "867" Y = "-609" T = "0" Pressure = "0" />
		<Point X = "874" Y = "-621" T = "0" Pressure = "0" />
		<Point X = "880" Y = "-632" T = "0" Pressure = "0" />
		<Point X = "886" Y = "-641" T = "0" Pressure = "0" />
		<Point X = "889" Y = "-647" T = "0" Pressure = "0" />
		<Point X = "891" Y = "-651" T = "0" Pressure = "0" />
		<Point X = "891" Y = "-652" T = "0" Pressure = "0" />
		<Point X = "892" Y = "-653" T = "0" Pressure = "0" />
		<Point X = "892" Y = "-653" T = "0" Pressure = "0" />
		<Point X = "892" Y = "-653" T = "0" Pressure = "0" />
		<Point X = "892" Y = "-653" T = "0" Pressure = "0" />
		<Point X = "892" Y = "-653" T = "0" Pressure = "0" />
		<Point X = "892" Y = "-653" T = "0" Pressure = "0" />
		<Point X = "892" Y = "-653" T = "0" Pressure = "0" />
		<Point X = "892" Y = "-653" T = "0" Pressure = "0" />
		<Point X = "892" Y = "-653" T = "0" Pressure = "0" />
		<Point X = "892" Y = "-653" T = "0" Pressure = "0" />
		<Point X = "892" Y = "-653" T = "0" Pressure = "0" />
		<Point X = "892" Y = "-653" T = "0" Pressure = "0" />
		<Point X = "892" Y = "-653" T = "0" Pressure = "0" />
		<Point X = "892" Y = "-653" T = "0" Pressure = "0" />
		<Point X = "892" Y = "-653" T = "0" Pressure = "0" />
		<Point X = "892" Y = "-653" T = "0" Pressure = "0" />
		<Point X = "892" Y = "-653" T = "0" Pressure = "0" />
		<Point X = "892" Y = "-653" T = "0" Pressure = "0" />
		<Point X = "892" Y = "-653" T = "0" Pressure = "0" />
		<Point X = "892" Y = "-653" T = "0" Pressure = "0" />
		<Point X = "892" Y = "-653" T = "0" Pressure = "0" />
		<Point X = "892" Y = "-653" T = "0" Pressure = "0" />
		<Point X = "892" Y = "-653" T = "0" Pressure = "0" />
		<Point X = "892" Y = "-653" T = "0" Pressure = "0" />
		<Point X = "892" Y = "-653" T = "0" Pressure = "0" />
		<Point X = "892" Y = "-653" T = "0" Pressure = "0" />
		<Point X = "892" Y = "-653" T = "0" Pressure = "0" />
		<Point X = "892" Y = "-653" T = "0" Pressure = "0" />
		<Point X = "892" Y = "-653" T = "0" Pressure = "0" />
		<Point X = "892" Y = "-653" T = "0" Pressure = "0" />
	</Stroke>
</Gesture>
