<?xml version="1.0" encoding="utf-8" standalone="yes"?>
<Gesture Name = "z">
	<Stroke>
		<Point X = "726" Y = "-549" T = "0" Pressure = "0" />
		<Point X = "726" Y = "-549" T = "0" Pressure = "0" />
		<Point X = "726" Y = "-550" T = "0" Pressure = "0" />
		<Point X = "726" Y = "-552" T = "0" Pressure = "0" />
		<Point X = "728" Y = "-556" T = "0" Pressure = "0" />
		<Point X = "728" Y = "-556" T = "0" Pressure = "0" />
		<Point X = "732" Y = "-560" T = "0" Pressure = "0" />
		<Point X = "738" Y = "-567" T = "0" Pressure = "0" />
		<Point X = "745" Y = "-574" T = "0" Pressure = "0" />
		<Point X = "755" Y = "-587" T = "0" Pressure = "0" />
		<Point X = "763" Y = "-600" T = "0" Pressure = "0" />
		<Point X = "782" Y = "-625" T = "0" Pressure = "0" />
		<Point X = "792" Y = "-640" T = "0" Pressure = "0" />
		<Point X = "800" Y = "-652" T = "0" Pressure = "0" />
		<Point X = "803" Y = "-663" T = "0" Pressure = "0" />
		<Point X = "808" Y = "-675" T = "0" Pressure = "0" />
		<Point X = "810" Y = "-684" T = "0" Pressure = "0" />
		<Point X = "811" Y = "-695" T = "0" Pressure = "0" />
		<Point X = "813" Y = "-700" T = "0" Pressure = "0" />
		<Point X = "813" Y = "-707" T = "0" Pressure = "0" />
		<Point X = "813" Y = "-713" T = "0" Pressure = "0" />
		<Point X = "813" Y = "-718" T = "0" Pressure = "0" />
		<Point X = "813" Y = "-720" T = "0" Pressure = "0" />
		<Point X = "812" Y = "-721" T = "0" Pressure = "0" />
		<Point X = "811" Y = "-723" T = "0" Pressure = "0" />
		<Point X = "810" Y = "-724" T = "0" Pressure = "0" />
		<Point X = "809" Y = "-724" T = "0" Pressure = "0" />
		<Point X = "805" Y = "-724" T = "0" Pressure = "0" />
		<Point X = "802" Y = "-726" T = "0" Pressure = "0" />
		<Point X = "796" Y = "-727" T = "0" Pressure = "0" />
		<Point X = "791" Y = "-727" T = "0" Pressure = "0" />
		<Point X = "786" Y = "-727" T = "0" Pressure = "0" />
		<Point X = "786" Y = "-727" T = "0" Pressure = "0" />
		<Point X = "780" Y = "-727" T = "0" Pressure = "0" />
		<Point X = "776" Y = "-727" T = "0" Pressure = "0" />
		<Point X = "771" Y = "-725" T = "0" Pressure = "0" />
		<Point X = "764" Y = "-723" T = "0" Pressure = "0" />
		<Point X = "760" Y = "-719" T = "0" Pressure = "0" />
		<Point X = "754" Y = "-714" T = "0" Pressure = "0" />
		<Point X = "747" Y = "-708" T = "0" Pressure = "0" />
		<Point X = "742" Y = "-700" T = "0" Pressure = "0" />
		<Point X = "739" Y = "-691" T = "0" Pressure = "0" />
		<Point X = "735" Y = "-682" T = "0" Pressure = "0" />
		<Point X = "734" Y = "-677" T = "0" Pressure = "0" />
		<Point X = "734" Y = "-670" T = "0" Pressure = "0" />
		<Point X = "734" Y = "-664" T = "0" Pressure = "0" />
		<Point X = "738" Y = "-660" T = "0" Pressure = "0" />
		<Point X = "743" Y = "-658" T = "0" Pressure = "0" />
		<Point X = "751" Y = "-653" T = "0" Pressure = "0" />
		<Point X = "758" Y = "-652" T = "0" Pressure = "0" />
		<Point X = "765" Y = "-652" T = "0" Pressure = "0" />
		<Point X = "765" Y = "-652" T = "0" Pressure = "0" />
		<Point X = "776" Y = "-652" T = "0" Pressure = "0" />
		<Point X = "785" Y = "-652" T = "0" Pressure = "0" />
		<Point X = "795" Y = "-652" T = "0" Pressure = "0" />
		<Point X = "804" Y = "-652" T = "0" Pressure = "0" />
		<Point X = "818" Y = "-656" T = "0" Pressure = "0" />
		<Point X = "829" Y = "-660" T = "0" Pressure = "0" />
		<Point X = "841" Y = "-665" T = "0" Pressure = "0" />
		<Point X = "851" Y = "-671" T = "0" Pressure = "0" />
		<Point X = "864" Y = "-676" T = "0" Pressure = "0" />
		<Point X = "878" Y = "-680" T = "0" Pressure = "0" />
		<Point X = "888" Y = "-686" T = "0" Pressure = "0" />
		<Point X = "898" Y = "-691" T = "0" Pressure = "0" />
		<Point X = "906" Y = "-693" T = "0" Pressure = "0" />
		<Point X = "916" Y = "-699" T = "0" Pressure = "0" />
		<Point X = "922" Y = "-703" T = "0" Pressure = "0" />
		<Point X = "929" Y = "-706" T = "0" Pressure = "0" />
		<Point X = "933" Y = "-709" T = "0" Pressure = "0" />
		<Point X = "934" Y = "-710" T = "0" Pressure = "0" />
		<Point X = "934" Y = "-710" T = "0" Pressure = "0" />
		<Point X = "936" Y = "-711" T = "0" Pressure = "0" />
		<Point X = "936" Y = "-711" T = "0" Pressure = "0" />
		<Point X = "936" Y = "-711" T = "0" Pressure = "0" />
		<Point X = "936" Y = "-711" T = "0" Pressure = "0" />
		<Point X = "937" Y = "-712" T = "0" Pressure = "0" />
		<Point X = "937" Y = "-712" T = "0" Pressure = "0" />
		<Point X = "937" Y = "-712" T = "0" Pressure = "0" />
		<Point X = "937" Y = "-712" T = "0" Pressure = "0" />
		<Point X = "937" Y = "-712" T = "0" Pressure = "0" />
		<Point X = "937" Y = "-712" T = "0" Pressure = "0" />
		<Point X = "937" Y = "-712" T = "0" Pressure = "0" />
		<Point X = "937" Y = "-712" T = "0" Pressure = "0" />
		<Point X = "937" Y = "-712" T = "0" Pressure = "0" />
		<Point X = "937" Y = "-712" T = "0" Pressure = "0" />
		<Point X = "937" Y = "-712" T = "0" Pressure = "0" />
		<Point X = "937" Y = "-712" T = "0" Pressure = "0" />
		<Point X = "937" Y = "-712" T = "0" Pressure = "0" />
		<Point X = "937" Y = "-712" T = "0" Pressure = "0" />
		<Point X = "937" Y = "-712" T = "0" Pressure = "0" />
		<Point X = "937" Y = "-712" T = "0" Pressure = "0" />
		<Point X = "937" Y = "-712" T = "0" Pressure = "0" />
		<Point X = "937" Y = "-712" T = "0" Pressure = "0" />
		<Point X = "937" Y = "-712" T = "0" Pressure = "0" />
		<Point X = "937" Y = "-712" T = "0" Pressure = "0" />
		<Point X = "937" Y = "-712" T = "0" Pressure = "0" />
		<Point X = "937" Y = "-712" T = "0" Pressure = "0" />
		<Point X = "937" Y = "-712" T = "0" Pressure = "0" />
		<Point X = "937" Y = "-712" T = "0" Pressure = "0" />
		<Point X = "937" Y = "-712" T = "0" Pressure = "0" />
		<Point X = "937" Y = "-712" T = "0" Pressure = "0" />
		<Point X = "937" Y = "-712" T = "0" Pressure = "0" />
		<Point X = "937" Y = "-712" T = "0" Pressure = "0" />
		<Point X = "937" Y = "-712" T = "0" Pressure = "0" />
		<Point X = "937" Y = "-712" T = "0" Pressure = "0" />
		<Point X = "937" Y = "-712" T = "0" Pressure = "0" />
		<Point X = "937" Y = "-712" T = "0" Pressure = "0" />
		<Point X = "937" Y = "-712" T = "0" Pressure = "0" />
		<Point X = "937" Y = "-712" T = "0" Pressure = "0" />
		<Point X = "937" Y = "-712" T = "0" Pressure = "0" />
		<Point X = "937" Y = "-712" T = "0" Pressure = "0" />
		<Point X = "937" Y = "-712" T = "0" Pressure = "0" />
		<Point X = "937" Y = "-712" T = "0" Pressure = "0" />
		<Point X = "937" Y = "-712" T = "0" Pressure = "0" />
		<Point X = "937" Y = "-712" T = "0" Pressure = "0" />
		<Point X = "937" Y = "-712" T = "0" Pressure = "0" />
		<Point X = "937" Y = "-712" T = "0" Pressure = "0" />
		<Point X = "937" Y = "-712" T = "0" Pressure = "0" />
		<Point X = "937" Y = "-712" T = "0" Pressure = "0" />
		<Point X = "937" Y = "-712" T = "0" Pressure = "0" />
		<Point X = "937" Y = "-712" T = "0" Pressure = "0" />
		<Point X = "937" Y = "-712" T = "0" Pressure = "0" />
		<Point X = "937" Y = "-712" T = "0" Pressure = "0" />
		<Point X = "937" Y = "-712" T = "0" Pressure = "0" />
		<Point X = "937" Y = "-712" T = "0" Pressure = "0" />
		<Point X = "937" Y = "-712" T = "0" Pressure = "0" />
		<Point X = "938" Y = "-710" T = "0" Pressure = "0" />
		<Point X = "936" Y = "-705" T = "0" Pressure = "0" />
		<Point X = "926" Y = "-692" T = "0" Pressure = "0" />
		<Point X = "924" Y = "-685" T = "0" Pressure = "0" />
		<Point X = "924" Y = "-685" T = "0" Pressure = "0" />
		<Point X = "897" Y = "-647" T = "0" Pressure = "0" />
		<Point X = "897" Y = "-647" T = "0" Pressure = "0" />
		<Point X = "887" Y = "-632" T = "0" Pressure = "0" />
		<Point X = "875" Y = "-617" T = "0" Pressure = "0" />
		<Point X = "868" Y = "-606" T = "0" Pressure = "0" />
		<Point X = "860" Y = "-595" T = "0" Pressure = "0" />
		<Point X = "854" Y = "-589" T = "0" Pressure = "0" />
		<Point X = "854" Y = "-589" T = "0" Pressure = "0" />
		<Point X = "854" Y = "-589" T = "0" Pressure = "0" />
		<Point X = "841" Y = "-572" T = "0" Pressure = "0" />
		<Point X = "840" Y = "-571" T = "0" Pressure = "0" />
		<Point X = "839" Y = "-571" T = "0" Pressure = "0" />
		<Point X = "839" Y = "-570" T = "0" Pressure = "0" />
		<Point X = "839" Y = "-570" T = "0" Pressure = "0" />
		<Point X = "839" Y = "-570" T = "0" Pressure = "0" />
		<Point X = "839" Y = "-570" T = "0" Pressure = "0" />
		<Point X = "839" Y = "-570" T = "0" Pressure = "0" />
		<Point X = "839" Y = "-570" T = "0" Pressure = "0" />
		<Point X = "839" Y = "-570" T = "0" Pressure = "0" />
		<Point X = "839" Y = "-570" T = "0" Pressure = "0" />
		<Point X = "839" Y = "-570" T = "0" Pressure = "0" />
		<Point X = "839" Y = "-570" T = "0" Pressure = "0" />
		<Point X = "839" Y = "-570" T = "0" Pressure = "0" />
		<Point X = "839" Y = "-570" T = "0" Pressure = "0" />
		<Point X = "839" Y = "-570" T = "0" Pressure = "0" />
		<Point X = "839" Y = "-570" T = "0" Pressure = "0" />
		<Point X = "839" Y = "-570" T = "0" Pressure = "0" />
		<Point X = "842" Y = "-570" T = "0" Pressure = "0" />
		<Point X = "842" Y = "-570" T = "0" Pressure = "0" />
		<Point X = "842" Y = "-570" T = "0" Pressure = "0" />
		<Point X = "846" Y = "-571" T = "0" Pressure = "0" />
		<Point X = "850" Y = "-573" T = "0" Pressure = "0" />
		<Point X = "854" Y = "-574" T = "0" Pressure = "0" />
		<Point X = "859" Y = "-575" T = "0" Pressure = "0" />
		<Point X = "866" Y = "-575" T = "0" Pressure = "0" />
		<Point X = "870" Y = "-576" T = "0" Pressure = "0" />
		<Point X = "881" Y = "-576" T = "0" Pressure = "0" />
		<Point X = "888" Y = "-576" T = "0" Pressure = "0" />
		<Point X = "893" Y = "-576" T = "0" Pressure = "0" />
		<Point X = "899" Y = "-575" T = "0" Pressure = "0" />
		<Point X = "905" Y = "-570" T = "0" Pressure = "0" />
		<Point X = "912" Y = "-565" T = "0" Pressure = "0" />
		<Point X = "918" Y = "-560" T = "0" Pressure = "0" />
		<Point X = "924" Y = "-554" T = "0" Pressure = "0" />
		<Point X = "931" Y = "-543" T = "0" Pressure = "0" />
		<Point X = "934" Y = "-532" T = "0" Pressure = "0" />
		<Point X = "938" Y = "-518" T = "0" Pressure = "0" />
		<Point X = "938" Y = "-506" T = "0" Pressure = "0" />
		<Point X = "938" Y = "-489" T = "0" Pressure = "0" />
		<Point X = "938" Y = "-469" T = "0" Pressure = "0" />
		<Point X = "937" Y = "-452" T = "0" Pressure = "0" />
		<Point X = "934" Y = "-433" T = "0" Pressure = "0" />
		<Point X = "932" Y = "-419" T = "0" Pressure = "0" />
		<Point X = "929" Y = "-403" T = "0" Pressure = "0" />
		<Point X = "927" Y = "-392" T = "0" Pressure = "0" />
		<Point X = "923" Y = "-380" T = "0" Pressure = "0" />
		<Point X = "919" Y = "-369" T = "0" Pressure = "0" />
		<Point X = "919" Y = "-369" T = "0" Pressure = "0" />
		<Point X = "913" Y = "-359" T = "0" Pressure = "0" />
		<Point X = "908" Y = "-350" T = "0" Pressure = "0" />
		<Point X = "902" Y = "-340" T = "0" Pressure = "0" />
		<Point X = "892" Y = "-331" T = "0" Pressure = "0" />
		<Point X = "881" Y = "-321" T = "0" Pressure = "0" />
		<Point X = "872" Y = "-316" T = "0" Pressure = "0" />
		<Point X = "861" Y = "-309" T = "0" Pressure = "0" />
		<Point X = "847" Y = "-303" T = "0" Pressure = "0" />
		<Point X = "834" Y = "-299" T = "0" Pressure = "0" />
		<Point X = "819" Y = "-294" T = "0" Pressure = "0" />
		<Point X = "799" Y = "-292" T = "0" Pressure = "0" />
		<Point X = "784" Y = "-289" T = "0" Pressure = "0" />
		<Point X = "770" Y = "-288" T = "0" Pressure = "0" />
		<Point X = "756" Y = "-288" T = "0" Pressure = "0" />
		<Point X = "743" Y = "-289" T = "0" Pressure = "0" />
		<Point X = "734" Y = "-293" T = "0" Pressure = "0" />
		<Point X = "722" Y = "-298" T = "0" Pressure = "0" />
		<Point X = "722" Y = "-298" T = "0" Pressure = "0" />
		<Point X = "713" Y = "-307" T = "0" Pressure = "0" />
		<Point X = "705" Y = "-314" T = "0" Pressure = "0" />
		<Point X = "697" Y = "-331" T = "0" Pressure = "0" />
		<Point X = "697" Y = "-346" T = "0" Pressure = "0" />
		<Point X = "697" Y = "-365" T = "0" Pressure = "0" />
		<Point X = "699" Y = "-383" T = "0" Pressure = "0" />
		<Point X = "709" Y = "-399" T = "0" Pressure = "0" />
		<Point X = "719" Y = "-414" T = "0" Pressure = "0" />
		<Point X = "728" Y = "-428" T = "0" Pressure = "0" />
		<Point X = "743" Y = "-443" T = "0" Pressure = "0" />
		<Point X = "759" Y = "-455" T = "0" Pressure = "0" />
		<Point X = "777" Y = "-467" T = "0" Pressure = "0" />
		<Point X = "795" Y = "-479" T = "0" Pressure = "0" />
		<Point X = "814" Y = "-488" T = "0" Pressure = "0" />
		<Point X = "832" Y = "-497" T = "0" Pressure = "0" />
		<Point X = "853" Y = "-504" T = "0" Pressure = "0" />
		<Point X = "876" Y = "-510" T = "0" Pressure = "0" />
		<Point X = "897" Y = "-516" T = "0" Pressure = "0" />
		<Point X = "918" Y = "-524" T = "0" Pressure = "0" />
		<Point X = "918" Y = "-524" T = "0" Pressure = "0" />
		<Point X = "958" Y = "-534" T = "0" Pressure = "0" />
		<Point X = "979" Y = "-540" T = "0" Pressure = "0" />
		<Point X = "1003" Y = "-548" T = "0" Pressure = "0" />
		<Point X = "1026" Y = "-554" T = "0" Pressure = "0" />
		<Point X = "1049" Y = "-560" T = "0" Pressure = "0" />
		<Point X = "1049" Y = "-560" T = "0" Pressure = "0" />
		<Point X = "1068" Y = "-564" T = "0" Pressure = "0" />
		<Point X = "1080" Y = "-568" T = "0" Pressure = "0" />
		<Point X = "1089" Y = "-571" T = "0" Pressure = "0" />
		<Point X = "1096" Y = "-574" T = "0" Pressure = "0" />
		<Point X = "1097" Y = "-574" T = "0" Pressure = "0" />
		<Point X = "1098" Y = "-574" T = "0" Pressure = "0" />
		<Point X = "1099" Y = "-575" T = "0" Pressure = "0" />
		<Point X = "1099" Y = "-575" T = "0" Pressure = "0" />
		<Point X = "1099" Y = "-575" T = "0" Pressure = "0" />
		<Point X = "1099" Y = "-575" T = "0" Pressure = "0" />
		<Point X = "1099" Y = "-575" T = "0" Pressure = "0" />
		<Point X = "1099" Y = "-575" T = "0" Pressure = "0" />
		<Point X = "1099" Y = "-575" T = "0" Pressure = "0" />
		<Point X = "1099" Y = "-575" T = "0" Pressure = "0" />
		<Point X = "1099" Y = "-575" T = "0" Pressure = "0" />
		<Point X = "1099" Y = "-575" T = "0" Pressure = "0" />
		<Point X = "1099" Y = "-575" T = "0" Pressure = "0" />
		<Point X = "1099" Y = "-575" T = "0" Pressure = "0" />
		<Point X = "1099" Y = "-575" T = "0" Pressure = "0" />
		<Point X = "1099" Y = "-575" T = "0" Pressure = "0" />
		<Point X = "1099" Y = "-575" T = "0" Pressure = "0" />
		<Point X = "1099" Y = "-575" T = "0" Pressure = "0" />
		<Point X = "1099" Y = "-575" T = "0" Pressure = "0" />
		<Point X = "1099" Y = "-575" T = "0" Pressure = "0" />
		<Point X = "1099" Y = "-575" T = "0" Pressure = "0" />
		<Point X = "1099" Y = "-575" T = "0" Pressure = "0" />
	</Stroke>
</Gesture>
